data_sitter/Contract.py
data_sitter/FieldResolver.py
data_sitter/Validation.py
data_sitter/__init__.py
data_sitter/cli.py
data_sitter/field_types/BaseField.py
data_sitter/field_types/FieldTypes.py
data_sitter/field_types/FloatField.py
data_sitter/field_types/IntegerField.py
data_sitter/field_types/NumericField.py
data_sitter/field_types/StringField.py
data_sitter/field_types/__init__.py
data_sitter/rules/Enums.py
data_sitter/rules/LogicalRule.py
data_sitter/rules/MatchedRule.py
data_sitter/rules/ProcessedRule.py
data_sitter/rules/Rule.py
data_sitter/rules/RuleRegistry.py
data_sitter/rules/__init__.py
data_sitter/rules/Parser/RuleParser.py
data_sitter/rules/Parser/__init__.py
data_sitter/rules/Parser/alias_parameters_parser.py
data_sitter/rules/Parser/parser_utils.py
data_sitter/utils/__init__.py
data_sitter/utils/logger_config.py
data_sitter-0.1.6.dist-info/METADATA
data_sitter-0.1.6.dist-info/WHEEL
data_sitter-0.1.6.dist-info/entry_points.txt
data_sitter-0.1.6.dist-info/top_level.txt
data_sitter-0.1.6.dist-info/RECORD
