Metadata-Version: 2.4
Name: data-sitter
Version: 0.1.6
Summary: A Python library that reads data contracts and generates Pydantic models for seamless data validation.
Author-email: Lázaro Pereira Candea <lazaro@candea.es>
Requires-Python: >=3.8
Requires-Dist: python-dotenv==1.0.1
Requires-Dist: PyYAML==6.0.2
Requires-Dist: parse_type==0.6.4
Requires-Dist: pydantic==2.10.5
Provides-Extra: dev
Requires-Dist: pytest==8.3.5; extra == "dev"
Requires-Dist: pytest-cov==6.0.0; extra == "dev"
Requires-Dist: pytest-mock==3.14.0; extra == "dev"
Requires-Dist: twine==6.1.0; extra == "dev"
Requires-Dist: build==1.2.2.post1; extra == "dev"
